viu/viu.py
viu-0.0.3.dist-info/LICENSE
viu-0.0.3.dist-info/METADATA
viu-0.0.3.dist-info/WHEEL
viu-0.0.3.dist-info/entry_points.txt
viu-0.0.3.dist-info/top_level.txt
viu-0.0.3.dist-info/RECORD
