Metadata-Version: 2.1
Name: viu
Version: 0.0.3
Summary: A small less-like Python code viewer with responsive formatting and styling
Home-page: http://github.com/fkohlgrueber/viu
Author: Felix Kohlgrüber
Author-email: felix.kohlgrueber@gmail.com
License: UNKNOWN
Platform: UNKNOWN
Classifier: Development Status :: 3 - Alpha
Classifier: Environment :: Console
Classifier: Operating System :: Unix
Classifier: Programming Language :: Python :: 3.6
Classifier: Programming Language :: Python :: 3.7
Classifier: License :: OSI Approved :: MIT License
Requires-Dist: black
Requires-Dist: pygments
Requires-Dist: click
